fnet_test_pip/__init__.py
fnet_test_pip/cli/__init__.py
fnet_test_pip/cli/index.py
fnet_test_pip/lib/__init__.py
fnet_test_pip/lib/index.py
fnet_test_pip-0.1.1.dist-info/METADATA
fnet_test_pip-0.1.1.dist-info/WHEEL
fnet_test_pip-0.1.1.dist-info/entry_points.txt
fnet_test_pip-0.1.1.dist-info/top_level.txt
fnet_test_pip-0.1.1.dist-info/RECORD
